specd/__init__.py
specd/app.py
specd/cli.py
specd/model.py
specd/monkey_patch.py
specd/new_specd.yaml
specd/tasks.py
specd/utils.py
specd/walker.py
specd/sdk/__init__.py
specd/sdk/client_async.py
specd/sdk/client_sync.py
specd/sdk/create.py
specd/sdk/functions.py
specd/sdk/model.py
specd-0.8.3.dist-info/LICENSE
specd-0.8.3.dist-info/METADATA
specd-0.8.3.dist-info/WHEEL
specd-0.8.3.dist-info/entry_points.txt
specd-0.8.3.dist-info/top_level.txt
specd-0.8.3.dist-info/RECORD
