Metadata-Version: 2.1
Name: specd
Version: 0.8.3
Summary: specd
Home-page: UNKNOWN
Author: Ian Maurer
Author-email: ian@genomoncology.com
License: MIT license
Keywords: Swagger Open API Specification Bravado
Platform: UNKNOWN
Classifier: Development Status :: 4 - Beta
Classifier: Intended Audience :: Developers
Classifier: License :: OSI Approved :: MIT License
Classifier: Natural Language :: English
Classifier: Programming Language :: Python :: 3
Classifier: Programming Language :: Python :: 3.6
License-File: LICENSE
Requires-Dist: click (>=6.7)
Requires-Dist: flask-swagger-ui (>=3.6.0)
Requires-Dist: swagger-spec-validator (>=2.1.0)
Requires-Dist: PyYAML (>=4.2b1)
Requires-Dist: dictdiffer (>=0.7.1)
Requires-Dist: related (>=0.7.3)
Requires-Dist: inflect (>=0.3.1)
Requires-Dist: aiobravado (==0.9.3)
Requires-Dist: bravado (==10.0.0)
Requires-Dist: bravado-core (==5.0.4)
Requires-Dist: bravado-asyncio (==1.0.0)
Requires-Dist: stringcase (>=1.2.0)
Requires-Dist: jsonschema[format]
Requires-Dist: urllib3 (>=1.24.2)
Requires-Dist: Jinja2 (>=2.10.1)
